pycompool/__init__.py
pycompool/cli.py
pycompool/commands.py
pycompool/connection.py
pycompool/controller.py
pycompool/monitor.py
pycompool/protocol.py
pycompool-0.2.3.dist-info/licenses/LICENSE
pycompool-0.2.3.dist-info/METADATA
pycompool-0.2.3.dist-info/WHEEL
pycompool-0.2.3.dist-info/entry_points.txt
pycompool-0.2.3.dist-info/top_level.txt
pycompool-0.2.3.dist-info/RECORD
