Metadata-Version: 2.4
Name: pycompool
Version: 0.2.3
Summary: Control Pentair/Compool LX3xxx pool and spa systems via RS-485
Author: pycompool contributors
License: MIT
Project-URL: Homepage, https://github.com/mcolyer/pycompool
Project-URL: Repository, https://github.com/mcolyer/pycompool
Project-URL: Issues, https://github.com/mcolyer/pycompool/issues
Classifier: Development Status :: 3 - Alpha
Classifier: Intended Audience :: Developers
Classifier: License :: OSI Approved :: MIT License
Classifier: Operating System :: OS Independent
Classifier: Programming Language :: Python :: 3
Classifier: Programming Language :: Python :: 3.9
Classifier: Programming Language :: Python :: 3.10
Classifier: Programming Language :: Python :: 3.11
Classifier: Programming Language :: Python :: 3.12
Classifier: Programming Language :: Python :: 3.13
Classifier: Topic :: Home Automation
Classifier: Topic :: System :: Hardware
Requires-Python: >=3.9
License-File: LICENSE
Requires-Dist: fire>=0.7.0
Requires-Dist: pyserial>=3.5
Provides-Extra: dev
Requires-Dist: pytest>=7.0; extra == "dev"
Requires-Dist: pytest-cov>=4.0; extra == "dev"
Requires-Dist: ruff>=0.1.0; extra == "dev"
Requires-Dist: mypy>=1.0; extra == "dev"
Requires-Dist: pre-commit>=3.0; extra == "dev"
Dynamic: license-file
